odoo10_addon_l10n_fr_base_location_geonames_import-10.0.1.0.0.99.dev4-py2.7-nspkg.pth
odoo/addons/l10n_fr_base_location_geonames_import/README.rst
odoo/addons/l10n_fr_base_location_geonames_import/__init__.py
odoo/addons/l10n_fr_base_location_geonames_import/__manifest__.py
odoo/addons/l10n_fr_base_location_geonames_import/i18n/l10n_fr_base_location_geonames_import.pot
odoo/addons/l10n_fr_base_location_geonames_import/i18n/nb_NO.po
odoo/addons/l10n_fr_base_location_geonames_import/static/description/icon.png
odoo/addons/l10n_fr_base_location_geonames_import/wizard/__init__.py
odoo/addons/l10n_fr_base_location_geonames_import/wizard/geonames_import.py
odoo10_addon_l10n_fr_base_location_geonames_import-10.0.1.0.0.99.dev4.dist-info/METADATA
odoo10_addon_l10n_fr_base_location_geonames_import-10.0.1.0.0.99.dev4.dist-info/RECORD
odoo10_addon_l10n_fr_base_location_geonames_import-10.0.1.0.0.99.dev4.dist-info/WHEEL
odoo10_addon_l10n_fr_base_location_geonames_import-10.0.1.0.0.99.dev4.dist-info/namespace_packages.txt
odoo10_addon_l10n_fr_base_location_geonames_import-10.0.1.0.0.99.dev4.dist-info/top_level.txt
