Metadata-Version: 2.1
Name: odoo10-addon-l10n-fr-base-location-geonames-import
Version: 10.0.1.0.0.99.dev4
Summary: France-specific tuning for import of better zip entries from Geonames
Home-page: http://www.akretion.com
Author: Akretion,Odoo Community Association (OCA)
Author-email: support@odoo-community.org
License: AGPL-3
Platform: UNKNOWN
Classifier: Programming Language :: Python
Classifier: Framework :: Odoo
Classifier: License :: OSI Approved :: GNU Affero General Public License v3
Requires-Python: ~=2.7
Requires-Dist: odoo10-addon-base-location-geonames-import
Requires-Dist: odoo (<10.1dev,>=10.0)
Requires-Dist: unidecode
